maxcompute_tea_util/__init__.py
maxcompute_tea_util/client.py
maxcompute_tea_util-0.0.1.dist-info/METADATA
maxcompute_tea_util-0.0.1.dist-info/WHEEL
maxcompute_tea_util-0.0.1.dist-info/top_level.txt
maxcompute_tea_util-0.0.1.dist-info/RECORD
